odoo/addons/partner_identification_unique_by_category/README.rst
odoo/addons/partner_identification_unique_by_category/__init__.py
odoo/addons/partner_identification_unique_by_category/__manifest__.py
odoo/addons/partner_identification_unique_by_category/i18n/es.po
odoo/addons/partner_identification_unique_by_category/i18n/it.po
odoo/addons/partner_identification_unique_by_category/i18n/partner_identification_unique_by_category.pot
odoo/addons/partner_identification_unique_by_category/models/__init__.py
odoo/addons/partner_identification_unique_by_category/models/res_partner_id_category.py
odoo/addons/partner_identification_unique_by_category/models/res_partner_id_number.py
odoo/addons/partner_identification_unique_by_category/readme/CONTRIBUTORS.md
odoo/addons/partner_identification_unique_by_category/readme/CREDITS.md
odoo/addons/partner_identification_unique_by_category/readme/DESCRIPTION.md
odoo/addons/partner_identification_unique_by_category/static/description/icon.png
odoo/addons/partner_identification_unique_by_category/static/description/index.html
odoo/addons/partner_identification_unique_by_category/tests/__init__.py
odoo/addons/partner_identification_unique_by_category/tests/test_partner_identification_unique_by_category.py
odoo/addons/partner_identification_unique_by_category/views/res_partner_id_category_view.xml
odoo_addon_partner_identification_unique_by_category-18.0.1.0.0.4.dist-info/METADATA
odoo_addon_partner_identification_unique_by_category-18.0.1.0.0.4.dist-info/WHEEL
odoo_addon_partner_identification_unique_by_category-18.0.1.0.0.4.dist-info/top_level.txt
odoo_addon_partner_identification_unique_by_category-18.0.1.0.0.4.dist-info/RECORD
