Metadata-Version: 2.1
Name: odoo-addon-partner_identification_unique_by_category
Version: 18.0.1.0.0.4
Requires-Python: >=3.10
Requires-Dist: odoo-addon-partner_identification==18.0.*
Requires-Dist: odoo==18.0.*
Summary: Partner Identification Numbers Unique By Category
Home-page: https://github.com/OCA/partner-contact
License: AGPL-3
Author: Camptocamp, Odoo Community Association (OCA)
Author-email: support@odoo-community.org
Classifier: Programming Language :: Python
Classifier: Framework :: Odoo
Classifier: Framework :: Odoo :: 18.0
Classifier: License :: OSI Approved :: GNU Affero General Public License v3
Classifier: Development Status :: 5 - Production/Stable
